airspot_ble/__init__.py
airspot_ble/client.py
airspot_ble/const.py
airspot_ble-1.0.0.dist-info/licenses/LICENSE
airspot_ble-1.0.0.dist-info/METADATA
airspot_ble-1.0.0.dist-info/WHEEL
airspot_ble-1.0.0.dist-info/top_level.txt
airspot_ble-1.0.0.dist-info/RECORD
