Metadata-Version: 2.4
Name: airspot-ble
Version: 1.0.0
Summary: Python library for interacting with Airspot devices via Bluetooth Low Energy (BLE)
Author-email: Airspot Health <support@airspothealth.com>
License: MIT
Project-URL: Homepage, https://github.com/AirSpotHealth/airspot-ble-python
Project-URL: Documentation, https://github.com/AirSpotHealth/airspot-ble-python#readme
Project-URL: Repository, https://github.com/AirSpotHealth/airspot-ble-python
Project-URL: Issues, https://github.com/AirSpotHealth/airspot-ble-python/issues
Keywords: ble,bluetooth,airspot,co2,sensor,home-assistant
Classifier: Development Status :: 3 - Alpha
Classifier: Intended Audience :: Developers
Classifier: License :: OSI Approved :: MIT License
Classifier: Programming Language :: Python :: 3
Classifier: Programming Language :: Python :: 3.10
Classifier: Programming Language :: Python :: 3.11
Classifier: Programming Language :: Python :: 3.12
Classifier: Programming Language :: Python :: 3.13
Requires-Python: >=3.10
License-File: LICENSE
Requires-Dist: bleak>=0.21.0
Provides-Extra: dev
Requires-Dist: pytest>=7.0; extra == "dev"
Requires-Dist: pytest-asyncio>=0.21.0; extra == "dev"
Requires-Dist: black>=23.0; extra == "dev"
Requires-Dist: ruff>=0.1.0; extra == "dev"
Dynamic: license-file
